hytk_model/__init__.py
hytk_model/hytk_detect.py
hytk_detect-0.0.2.dist-info/METADATA
hytk_detect-0.0.2.dist-info/WHEEL
hytk_detect-0.0.2.dist-info/top_level.txt
hytk_detect-0.0.2.dist-info/RECORD
