Metadata-Version: 2.1
Name: hytk-detect
Version: 0.0.2
Summary: UNKNOWN
Home-page: https://github.com/xuhuaren
Author: xuhua.ren
Author-email: renxuhua1993@gmail.com
License: UNKNOWN
Platform: UNKNOWN
Requires-Dist: numpy (==1.19.4)
Requires-Dist: Pillow (==8.0.0)
Requires-Dist: requests (==2.25.1)
Requires-Dist: requests-oauthlib (==1.3.0)
